depman/__init__.py
depman/apt.py
depman/dependency.py
depman/globals.py
depman/main.py
depman/metadata.yml
depman/operation.py
depman/pip.py
depman/relation.py
depman/yatr.py
depman/tests/__init__.py
depman/tests/test1
depman/tests/test1.yml
depman/tests/test_apt.py
depman/tests/test_dependency.py
depman/tests/test_file.py
depman/tests/test_main.py
depman/tests/test_operation.py
depman/tests/test_pip.py
depman/tests/test_relation.py
depman/tests/test_yatr.py
depman-0.3.4.dist-info/DESCRIPTION.rst
depman-0.3.4.dist-info/METADATA
depman-0.3.4.dist-info/RECORD
depman-0.3.4.dist-info/WHEEL
depman-0.3.4.dist-info/entry_points.txt
depman-0.3.4.dist-info/metadata.json
depman-0.3.4.dist-info/top_level.txt
