Metadata-Version: 2.0
Name: depman
Version: 0.3.4
Summary: A lightweight dependency manager
Home-page: https://github.com/mbodenhamer/depman
Author: Matt Bodenhamer
Author-email: mbodenhamer@mbodenhamer.com
License: MIT
Keywords: dependencies,dependency management
Platform: UNKNOWN
Classifier: Development Status :: 3 - Alpha
Classifier: Environment :: Console
Classifier: Intended Audience :: Developers
Classifier: Intended Audience :: System Administrators
Classifier: License :: OSI Approved :: MIT License
Classifier: Operating System :: POSIX :: Linux
Classifier: Programming Language :: Python
Classifier: Programming Language :: Python :: 2.7
Classifier: Programming Language :: Python :: 3.6
Classifier: Topic :: Utilities
Requires-Dist: syn
Requires-Dist: yatr
